gwaxion/__init__.py
gwaxion/evolve.py
gwaxion/leavers.py
gwaxion/parallel.py
gwaxion/physics.py
gwaxion/utilities.py
gwaxion-0.0.1.dist-info/LICENSE
gwaxion-0.0.1.dist-info/METADATA
gwaxion-0.0.1.dist-info/WHEEL
gwaxion-0.0.1.dist-info/top_level.txt
gwaxion-0.0.1.dist-info/RECORD
