Metadata-Version: 2.1
Name: gwaxion
Version: 0.0.1
Summary: Black-hole boson gravitational-wave package.
Home-page: https://github.com/maxisi/gwaxion
Author: Maximiliano Isi
Author-email: max.isi@ligo.org
License: UNKNOWN
Platform: UNKNOWN
Classifier: Intended Audience :: Science/Research
Classifier: Natural Language :: English
Classifier: Topic :: Scientific/Engineering :: Physics
Classifier: Topic :: Scientific/Engineering :: Astronomy
Classifier: Programming Language :: Python :: 3
Classifier: License :: OSI Approved :: MIT License
Classifier: Operating System :: OS Independent
Requires-Python: >=3.6
Requires-Dist: numpy
Requires-Dist: scipy
